{
  "project_info": {
    "project_number": "549871453740",
    "firebase_url": "https://plcnurse.firebaseio.com",
    "project_id": "plcnurse",
    "storage_bucket": "plcnurse.appspot.com"
  },
  "client": [
    {
      "client_info": {
        "mobilesdk_app_id": "1:549871453740:android:7a2590cd4669e9f6",
        "android_client_info": {
          "package_name": "gkrgroup.com.plcnurse"
        }
      },
      "oauth_client": [
        {
          "client_id": "549871453740-pqfok2b40ntatrmi5obc0980tii25k8j.apps.googleusercontent.com",
          "client_type": 3
        }
      ],
      "api_key": [
        {
          "current_key": "AIzaSyCR3ozS-fMz1jIXhFm3NVOus301ja8bQAw"
        }
      ],
      "services": {
        "appinvite_service": {
          "other_platform_oauth_client": [
            {
              "client_id": "549871453740-pqfok2b40ntatrmi5obc0980tii25k8j.apps.googleusercontent.com",
              "client_type": 3
            }
          ]
        }
      }
    }
  ],
  "configuration_version": "1"
}